lot/__init__.py
lot/animation.py
lot/calculate.py
lot/main.py
lot/sample.py
lot/visualization.py
lot/algorithms/__init__.py
lot/algorithms/base.py
lot/algorithms/prompt.py
lot/algorithms/utils.py
lot/algorithms/Tree/MCTS/__init__.py
lot/algorithms/Tree/MCTS/args.md
lot/algorithms/Tree/MCTS/base.py
lot/algorithms/Tree/MCTS/mcts.py
lot/algorithms/Tree/MCTS/task.py
lot/algorithms/Tree/ToT/__init__.py
lot/algorithms/Tree/ToT/base.py
lot/algorithms/Tree/ToT/bfs.py
lot/algorithms/Tree/ToT/dfs.py
lot/algorithms/Tree/ToT/task.py
lot/algorithms/Tree/tasks/__init__.py
lot/algorithms/Tree/tasks/prompts.py
lot/algorithms/Tree/tasks/science.py
lot/algorithms/Tree/utils/__init__.py
lot/algorithms/Tree/utils/aggregate_value_samples.py
lot/algorithms/Tree/utils/answer_extractor.py
lot/algorithms/Tree/utils/extract_both_samples.py
lot/algorithms/Tree/utils/format_dpo.py
lot/algorithms/Tree/utils/json_operator.py
lot/algorithms/Tree/utils/orm_score.py
lot/algorithms/Tree/utils/result_evaluator.py
lot/algorithms/Tree/utils/self_consistency.py
lot/algorithms/Tree/utils/solution_summary_extractor.py
lot/algorithms/Tree/utils/verify_MATH.py
lot/algorithms/Tree/utils/verify_answer.py
lot/algorithms/Tree/utils/verify_llm.py
lot/algorithms/Tree/utils/visualize.py
lot/algorithms/Tree/utils/weighted_consistency.py
lot/data/aqua.jsonl
lot/data/commonsenseqa.jsonl
lot/data/dummy.jsonl
lot/data/mmlu.json
lot/data/strategyqa.json
lot/datasets/__init__.py
lot/datasets/base.py
lot/datasets/dataset_loader.py
lot/datasets/json_dataset.py
lot/datasets/prompt.py
lot/datasets/utils.py
lot/examples/update_models.py
lot/models/__init__.py
lot/models/adapter.py
lot/models/api_calling.py
lot/models/base.py
lot/models/utils.py
lot/models/data/togetherAI_model_infos.json
lot/visualization_utils/__init__.py
lot/visualization_utils/landscape.py
lot/visualization_utils/utils.py
landscape_of_thoughts-0.1.0.dist-info/METADATA
landscape_of_thoughts-0.1.0.dist-info/WHEEL
landscape_of_thoughts-0.1.0.dist-info/entry_points.txt
landscape_of_thoughts-0.1.0.dist-info/licenses/LICENSE.md
landscape_of_thoughts-0.1.0.dist-info/RECORD
