Metadata-Version: 2.4
Name: landscape-of-thoughts
Version: 0.1.0
Summary: Visualizing the Reasoning Process of Large Language Models
Project-URL: Paper, https://arxiv.org/abs/2503.22165
Project-URL: Homepage, https://github.com/tmlr-group/landscape-of-thoughts
Project-URL: Bug Tracker, https://github.com/tmlr-group/landscape-of-thoughts/issues
Project-URL: Documentation, https://github.com/tmlr-group/landscape-of-thoughts
Author: Zhanke Zhou, Zhaocheng Zhu, Xuan Li, Mikhail Galkin, Xiao Feng, Sanmi Koyejo, Jian Tang, Bo Han
License: MIT
License-File: LICENSE.md
Keywords: landscape,llm,reasoning,thoughts,visualization
Classifier: Development Status :: 3 - Alpha
Classifier: Intended Audience :: Science/Research
Classifier: License :: OSI Approved :: MIT License
Classifier: Programming Language :: Python :: 3
Classifier: Programming Language :: Python :: 3.10
Classifier: Topic :: Scientific/Engineering :: Artificial Intelligence
Requires-Python: >=3.10
Requires-Dist: aiohttp>=3.11.13
Requires-Dist: aiosignal>=1.3.2
Requires-Dist: anyio>=4.8.0
Requires-Dist: async-timeout>=5.0.1
Requires-Dist: attrs>=25.1.0
Requires-Dist: certifi>=2025.1.31
Requires-Dist: charset-normalizer>=3.4.1
Requires-Dist: datasets>=3.3.2
Requires-Dist: fastapi>=0.115.11
Requires-Dist: filelock>=3.17.0
Requires-Dist: fire>=0.7.0
Requires-Dist: fsspec>=2024.12.0
Requires-Dist: httpx>=0.28.1
Requires-Dist: huggingface-hub>=0.29.2
Requires-Dist: joblib>=1.4.2
Requires-Dist: kaleido>=0.2.1
Requires-Dist: matplotlib>=3.10.0
Requires-Dist: nbformat>=4.2.0
Requires-Dist: numpy>=2.1.3
Requires-Dist: openai>=1.65.5
Requires-Dist: pandas>=2.2.3
Requires-Dist: pillow>=11.1.0
Requires-Dist: plotly>=5.24.0
Requires-Dist: pydantic>=2.10.6
Requires-Dist: pylatexenc>=2.10.0
Requires-Dist: python-dotenv>=1.0.1
Requires-Dist: pyyaml>=6.0.2
Requires-Dist: requests>=2.32.3
Requires-Dist: scikit-learn>=1.6.1
Requires-Dist: scipy>=1.15.2
Requires-Dist: sympy>=1.13.1
Requires-Dist: together>=1.5.5
Requires-Dist: tokenizers>=0.21.0
Requires-Dist: tqdm>=4.67.1
Requires-Dist: transformers>=4.49.0
Requires-Dist: typer>=0.15.2
Requires-Dist: urllib3>=2.3.0
Requires-Dist: uvicorn>=0.34.0
Provides-Extra: dev
Requires-Dist: black>=23.0.0; extra == 'dev'
Requires-Dist: flake8>=6.0.0; extra == 'dev'
Requires-Dist: isort>=5.10.0; extra == 'dev'
Requires-Dist: pytest>=7.0.0; extra == 'dev'
